{
    "count": 99,
    "discord": [
        {
            "postLink": "https://redd.it/1fy9kt4",
            "subreddit": "Discordmemes",
            "title": "1000 bottles",
            "url": "https://i.redd.it/l90z5l2blctd1.jpeg",
            "nsfw": false,
            "spoiler": false,
            "author": "TheGuyWhoAsked1014",
            "ups": 389
        },
        {
            "postLink": "https://redd.it/1fms8ht",
            "subreddit": "Discordmemes",
            "title": "Bro's username-\ud83e\udd21 Game bro is playing-\ud83d\udc7d",
            "url": "https://i.redd.it/piyavq4wucqd1.png",
            "nsfw": false,
            "spoiler": false,
            "author": "Nevil14655",
            "ups": 44
        },
        {
            "postLink": "https://redd.it/1fj0a1d",
            "subreddit": "Discordmemes",
            "title": "2 steps ahead, i am always, 2 steps ahead.",
            "url": "https://i.redd.it/t9k2z24fndpd1.png",
            "nsfw": false,
            "spoiler": false,
            "author": "ItzMe_EYB",
            "ups": 51
        },
        {
            "postLink": "https://redd.it/1em6z6k",
            "subreddit": "Discordmemes",
            "title": "To the MOON!!!",
            "url": "https://i.redd.it/gs9uix5ki7hd1.png",
            "nsfw": false,
            "spoiler": false,
            "author": "SharkyBoi2005",
            "ups": 95
        },
        {
            "postLink": "https://redd.it/1fehn55",
            "subreddit": "Discordmemes",
            "title": "one, two, four",
            "url": "https://i.redd.it/4uz5w1xx58od1.png",
            "nsfw": false,
            "spoiler": false,
            "author": "chinagreenelvis-art",
            "ups": 7
        },
        {
            "postLink": "https://redd.it/1fv6klv",
            "subreddit": "Discordmemes",
            "title": "A classic",
            "url": "https://i.redd.it/ttxhugxccjsd1.png",
            "nsfw": false,
            "spoiler": false,
            "author": "yukiyuki11",
            "ups": 70
        },
        {
            "postLink": "https://redd.it/1fgjq6y",
            "subreddit": "Discordmemes",
            "title": "Discord help",
            "url": "https://i.redd.it/h9is71uncrod1.png",
            "nsfw": false,
            "spoiler": false,
            "author": "Able_Tree3679",
            "ups": 0
        },
        {
            "postLink": "https://redd.it/1fpppiv",
            "subreddit": "Discordmemes",
            "title": "Discord meme #3",
            "url": "https://i.redd.it/egnsuvdyj3rd1.png",
            "nsfw": false,
            "spoiler": false,
            "author": "AleksKvas",
            "ups": 114
        },
        {
            "postLink": "https://redd.it/1ewkg7t",
            "subreddit": "Discordmemes",
            "title": "Cube Rule of Foods and Cinnamon Rolls it",
            "url": "https://i.redd.it/x9i755q4dqjd1.jpeg",
            "nsfw": false,
            "spoiler": false,
            "author": "SirBucketing",
            "ups": 36
        },
        {
            "postLink": "https://redd.it/1fcasf7",
            "subreddit": "Discordmemes",
            "title": "so easy",
            "url": "https://i.redd.it/jpa86owe1ond1.jpeg",
            "nsfw": false,
            "spoiler": false,
            "author": "Much-Reindeer-2633",
            "ups": 100
        },
        {
            "postLink": "https://redd.it/1fj2n16",
            "subreddit": "Discordmemes",
            "title": "Pou's backstory",
            "url": "https://i.redd.it/wa8wdcmn4epd1.jpeg",
            "nsfw": false,
            "spoiler": false,
            "author": "SuperMarket-of-Bing",
            "ups": 132
        },
        {
            "postLink": "https://redd.it/1fhdfbv",
            "subreddit": "Discordmemes",
            "title": "WHAT THE FUCK?",
            "url": "https://i.redd.it/c5huwhdtdzod1.png",
            "nsfw": false,
            "spoiler": false,
            "author": "Dry_Communication403",
            "ups": 6
        },
        {
            "postLink": "https://redd.it/1fpzp7t",
            "subreddit": "Discordmemes",
            "title": "Discord meme #4",
            "url": "https://i.redd.it/7tthkvy4f6rd1.jpeg",
            "nsfw": false,
            "spoiler": false,
            "author": "AleksKvas",
            "ups": 123
        },
        {
            "postLink": "https://redd.it/1ftk5dp",
            "subreddit": "Discordmemes",
            "title": "Brian",
            "url": "https://i.redd.it/yu0e0cq684sd1.jpeg",
            "nsfw": false,
            "spoiler": false,
            "author": "Jesp2_Official",
            "ups": 89
        },
        {
            "postLink": "https://redd.it/1fafdv6",
            "subreddit": "Discordmemes",
            "title": "What's wrong with people these days..",
            "url": "https://i.redd.it/x6sl3o1gz6nd1.png",
            "nsfw": false,
            "spoiler": false,
            "author": "ConsistentStranger42",
            "ups": 0
        },
        {
            "postLink": "https://redd.it/1f16yb2",
            "subreddit": "Discordmemes",
            "title": "rip to that guy",
            "url": "https://i.redd.it/x7t4pciykvkd1.png",
            "nsfw": false,
            "spoiler": false,
            "author": "RedditIsHeadless",
            "ups": 120
        },
        {
            "postLink": "https://redd.it/1elu7ch",
            "subreddit": "Discordmemes",
            "title": "real.",
            "url": "https://i.redd.it/u1ijr46b64hd1.jpeg",
            "nsfw": false,
            "spoiler": false,
            "author": "dawtieee",
            "ups": 213
        },
        {
            "postLink": "https://redd.it/1fje0f3",
            "subreddit": "Discordmemes",
            "title": "fr?",
            "url": "https://i.redd.it/qaszat9dcgpd1.png",
            "nsfw": false,
            "spoiler": false,
            "author": "YourPalLex",
            "ups": 105
        },
        {
            "postLink": "https://redd.it/1ey5dip",
            "subreddit": "Discordmemes",
            "title": "uh oh",
            "url": "https://i.redd.it/xllnphify3kd1.jpeg",
            "nsfw": false,
            "spoiler": false,
            "author": "cockman9797",
            "ups": 104
        },
        {
            "postLink": "https://redd.it/1fq00oz",
            "subreddit": "Discordmemes",
            "title": "Discord meme #9",
            "url": "https://i.redd.it/h1bsu3lhh6rd1.jpeg",
            "nsfw": false,
            "spoiler": false,
            "author": "AleksKvas",
            "ups": 16
        },
        {
            "postLink": "https://redd.it/1f3pqcx",
            "subreddit": "Discordmemes",
            "title": "on jah",
            "url": "https://i.redd.it/j2unbajo4ild1.jpeg",
            "nsfw": false,
            "spoiler": false,
            "author": "Aidenc93",
            "ups": 79
        },
        {
            "postLink": "https://redd.it/1f9v8hb",
            "subreddit": "Discordmemes",
            "title": "Possibly true ?!?",
            "url": "https://i.redd.it/tck0ttptv5md1.png",
            "nsfw": false,
            "spoiler": false,
            "author": "Henry4live",
            "ups": 1273
        },
        {
            "postLink": "https://redd.it/1fpgj3h",
            "subreddit": "Discordmemes",
            "title": "lmao",
            "url": "https://i.redd.it/ymlvw99b21rd1.png",
            "nsfw": false,
            "spoiler": false,
            "author": "Ilikesealslol",
            "ups": 24
        },
        {
            "postLink": "https://redd.it/1f9l8co",
            "subreddit": "Discordmemes",
            "title": "Imma jump",
            "url": "https://i.redd.it/pof95q6eizmd1.jpeg",
            "nsfw": false,
            "spoiler": false,
            "author": "TheGuyWhoAsked1014",
            "ups": 884
        },
        {
            "postLink": "https://redd.it/1fb3gvu",
            "subreddit": "Discordmemes",
            "title": "Discord becomes a monster",
            "url": "https://i.redd.it/r9ppz8lp1dnd1.png",
            "nsfw": false,
            "spoiler": false,
            "author": "StrangeBookkeeper940",
            "ups": 0
        },
        {
            "postLink": "https://redd.it/1fu3cea",
            "subreddit": "Discordmemes",
            "title": "Link in 1st comment",
            "url": "https://i.redd.it/uz9klennk8sd1.png",
            "nsfw": false,
            "spoiler": false,
            "author": "Kavinda999",
            "ups": 0
        },
        {
            "postLink": "https://redd.it/1fwyux7",
            "subreddit": "Discordmemes",
            "title": "Chat istg-",
            "url": "https://i.redd.it/2ps5y1ijtzsd1.jpeg",
            "nsfw": false,
            "spoiler": false,
            "author": "FloxOnPawz",
            "ups": 112
        },
        {
            "postLink": "https://redd.it/1fbfhq9",
            "subreddit": "Discordmemes",
            "title": "I like the questions!!!",
            "url": "https://i.redd.it/ek79elymyfnd1.jpeg",
            "nsfw": false,
            "spoiler": false,
            "author": "henry_the_destroyer",
            "ups": 16
        },
        {
            "postLink": "https://redd.it/1fv3kz9",
            "subreddit": "Discordmemes",
            "title": "Seriously, who cut her hair?",
            "url": "https://i.redd.it/3nmib6oedisd1.png",
            "nsfw": false,
            "spoiler": false,
            "author": "katiebug586",
            "ups": 40
        },
        {
            "postLink": "https://redd.it/1fnqcc1",
            "subreddit": "Discordmemes",
            "title": "ok",
            "url": "https://i.redd.it/xc4q99wlhlqd1.png",
            "nsfw": false,
            "spoiler": false,
            "author": "MorningCoffeeReddit",
            "ups": 55
        },
        {
            "postLink": "https://redd.it/1fzdbc4",
            "subreddit": "Discordmemes",
            "title": "Fish",
            "url": "https://i.redd.it/8clen3o96mtd1.jpeg",
            "nsfw": false,
            "spoiler": false,
            "author": "Oak_YT",
            "ups": 39
        },
        {
            "postLink": "https://redd.it/1f4ceyu",
            "subreddit": "Discordmemes",
            "title": "Dog rug",
            "url": "https://i.redd.it/0pou1xuzvnld1.png",
            "nsfw": false,
            "spoiler": false,
            "author": "DinoHawaii2021",
            "ups": 946
        },
        {
            "postLink": "https://redd.it/1eogcng",
            "subreddit": "Discordmemes",
            "title": "Anybody looking for a discord moderator? (M25)",
            "url": "https://i.redd.it/3krrp8qrjqhd1.jpeg",
            "nsfw": false,
            "spoiler": false,
            "author": "smbzbro119",
            "ups": 0
        },
        {
            "postLink": "https://redd.it/1ernj3m",
            "subreddit": "Discordmemes",
            "title": "Monster Rio Punch for me idk about you...",
            "url": "https://i.redd.it/nf12lhljwiid1.jpeg",
            "nsfw": false,
            "spoiler": false,
            "author": "SharkyBoi2005",
            "ups": 75
        },
        {
            "postLink": "https://redd.it/1fxy1wr",
            "subreddit": "Discordmemes",
            "title": "What the freak ",
            "url": "https://i.redd.it/nty8c86q29td1.png",
            "nsfw": false,
            "spoiler": false,
            "author": "youfartedlaterbruh",
            "ups": 55
        },
        {
            "postLink": "https://redd.it/1f6k0cr",
            "subreddit": "Discordmemes",
            "title": "average discord conversation",
            "url": "https://i.redd.it/w31lojveg8md1.png",
            "nsfw": false,
            "spoiler": false,
            "author": "danidev_alt",
            "ups": 62
        },
        {
            "postLink": "https://redd.it/1f7s4j9",
            "subreddit": "Discordmemes",
            "title": "I regret adding this bot already.",
            "url": "https://i.redd.it/gemewg8k4jmd1.png",
            "nsfw": false,
            "spoiler": false,
            "author": "weapingwillowiam",
            "ups": 133
        },
        {
            "postLink": "https://redd.it/1ev01tc",
            "subreddit": "Discordmemes",
            "title": "Something My Friend Sent Me",
            "url": "https://i.redd.it/or2h4fifgcjd1.png",
            "nsfw": false,
            "spoiler": false,
            "author": "Sargefan767",
            "ups": 628
        },
        {
            "postLink": "https://redd.it/1ethlxu",
            "subreddit": "Discordmemes",
            "title": "Poor bonnie",
            "url": "https://i.redd.it/su0op9rxxyid1.jpeg",
            "nsfw": false,
            "spoiler": false,
            "author": "[deleted]",
            "ups": 297
        },
        {
            "postLink": "https://redd.it/1fjpmwi",
            "subreddit": "Discordmemes",
            "title": "Listen I ain\u2019t got no patience ",
            "url": "https://i.redd.it/ol7gmgu3qjpd1.png",
            "nsfw": false,
            "spoiler": false,
            "author": "FloxOnPawz",
            "ups": 93
        },
        {
            "postLink": "https://redd.it/1fpjxw1",
            "subreddit": "Discordmemes",
            "title": "Discord meme #1",
            "url": "https://i.redd.it/5blcw0elv1rd1.gif",
            "nsfw": false,
            "spoiler": false,
            "author": "AleksKvas",
            "ups": 58
        },
        {
            "postLink": "https://redd.it/1flyg3q",
            "subreddit": "Discordmemes",
            "title": "Ahh",
            "url": "https://i.redd.it/7bblqt7qi4qd1.png",
            "nsfw": false,
            "spoiler": false,
            "author": "Repulsive-Wrap-958",
            "ups": 975
        },
        {
            "postLink": "https://redd.it/1fzhsfc",
            "subreddit": "Discordmemes",
            "title": "True?",
            "url": "https://i.redd.it/xj03f7j5bntd1.jpeg",
            "nsfw": false,
            "spoiler": false,
            "author": "sum1elseidk",
            "ups": 261
        },
        {
            "postLink": "https://redd.it/1ftknmj",
            "subreddit": "Discordmemes",
            "title": "The way he just said ok",
            "url": "https://i.redd.it/rqkds5zke4sd1.jpeg",
            "nsfw": false,
            "spoiler": false,
            "author": "Local_dumbass173",
            "ups": 30
        },
        {
            "postLink": "https://redd.it/1g10vw0",
            "subreddit": "Discordmemes",
            "title": "I'm on a seafood diet (I see food and i eat it)",
            "url": "https://i.redd.it/6hphcew9s1ud1.png",
            "nsfw": false,
            "spoiler": false,
            "author": "SnailStropod",
            "ups": 76
        },
        {
            "postLink": "https://redd.it/1eso6hh",
            "subreddit": "Discordmemes",
            "title": "can i atleast get 50 bucks for effort? - scammer and hacker that hacked my own account",
            "url": "https://i.redd.it/2ndwy9j8urid1.png",
            "nsfw": false,
            "spoiler": false,
            "author": "[deleted]",
            "ups": 102
        },
        {
            "postLink": "https://redd.it/1fc4lxz",
            "subreddit": "Discordmemes",
            "title": "I found this from a Discord server ",
            "url": "https://i.redd.it/bk2wryl8pmnd1.gif",
            "nsfw": false,
            "spoiler": false,
            "author": "Embarrassed-Book7904",
            "ups": 45
        },
        {
            "postLink": "https://redd.it/1fntq39",
            "subreddit": "Discordmemes",
            "title": "Don't mess with Belgium!",
            "url": "https://i.redd.it/kbxthxr56mqd1.png",
            "nsfw": false,
            "spoiler": false,
            "author": "urnanny123",
            "ups": 23
        },
        {
            "postLink": "https://redd.it/1frng1r",
            "subreddit": "Discordmemes",
            "title": "Not really a meme but",
            "url": "https://i.redd.it/aweh23ec1mrd1.png",
            "nsfw": false,
            "spoiler": false,
            "author": "Background_Top8251",
            "ups": 44
        },
        {
            "postLink": "https://redd.it/1ffict4",
            "subreddit": "Discordmemes",
            "title": "What did my freind just send dude",
            "url": "https://i.redd.it/blu0i0qk6hod1.jpeg",
            "nsfw": false,
            "spoiler": false,
            "author": "womenhaver69",
            "ups": 410
        },
        {
            "postLink": "https://redd.it/1er5nhz",
            "subreddit": "Discordmemes",
            "title": "oh ok",
            "url": "https://i.redd.it/o36bq7bt4fid1.jpeg",
            "nsfw": false,
            "spoiler": false,
            "author": "megatracercon2",
            "ups": 315
        },
        {
            "postLink": "https://redd.it/1fpb4yr",
            "subreddit": "Discordmemes",
            "title": "HOW?",
            "url": "https://i.redd.it/bnzy19z8xzqd1.jpeg",
            "nsfw": false,
            "spoiler": false,
            "author": "Beneficial_Trash9708",
            "ups": 189
        },
        {
            "postLink": "https://redd.it/1fppnh7",
            "subreddit": "Discordmemes",
            "title": "Discord #2 (A bit to relatable",
            "url": "https://i.redd.it/sxnqmbb9j3rd1.png",
            "nsfw": false,
            "spoiler": false,
            "author": "AleksKvas",
            "ups": 19
        },
        {
            "postLink": "https://redd.it/1emq2od",
            "subreddit": "Discordmemes",
            "title": "\ud83d\udde3\ufe0f\ud83d\ude4f\ud83d\udd25",
            "url": "https://i.redd.it/cegc16a2obhd1.gif",
            "nsfw": false,
            "spoiler": false,
            "author": "Constinti",
            "ups": 26
        },
        {
            "postLink": "https://redd.it/1fgyu2m",
            "subreddit": "Discordmemes",
            "title": "They're fucked up",
            "url": "https://i.redd.it/72rdqrtuyuod1.png",
            "nsfw": false,
            "spoiler": false,
            "author": "Dry_Communication403",
            "ups": 1
        },
        {
            "postLink": "https://redd.it/1frir3r",
            "subreddit": "Discordmemes",
            "title": "soon",
            "url": "https://i.redd.it/2vze8tq8zkrd1.png",
            "nsfw": false,
            "spoiler": false,
            "author": "Ok-Copy2156",
            "ups": 164
        },
        {
            "postLink": "https://redd.it/1fbqwc3",
            "subreddit": "Discordmemes",
            "title": "Anybody... anyone... someone...",
            "url": "https://i.redd.it/yy6m6xdvyind1.png",
            "nsfw": false,
            "spoiler": false,
            "author": "666Lucifer999_",
            "ups": 20
        },
        {
            "postLink": "https://redd.it/1f15t3r",
            "subreddit": "Discordmemes",
            "title": "Real",
            "url": "https://i.redd.it/r1sivc76cvkd1.jpeg",
            "nsfw": false,
            "spoiler": false,
            "author": "OriginalWorking1647",
            "ups": 2351
        },
        {
            "postLink": "https://redd.it/1ezquwu",
            "subreddit": "Discordmemes",
            "title": "no suc thing",
            "url": "https://i.redd.it/b7g04u47yhkd1.png",
            "nsfw": false,
            "spoiler": false,
            "author": "DrLycFerno",
            "ups": 31
        },
        {
            "postLink": "https://redd.it/1fpsp0j",
            "subreddit": "Discordmemes",
            "title": "Remember boys and girls. Dont lurk in invis.",
            "url": "https://i.redd.it/21m7tb2ho4rd1.png",
            "nsfw": false,
            "spoiler": false,
            "author": "Thedemonbehindu",
            "ups": 64
        },
        {
            "postLink": "https://redd.it/1fsbcfy",
            "subreddit": "Discordmemes",
            "title": "Look what one of my bros sent to me ",
            "url": "https://i.redd.it/ixlr4lg0msrd1.png",
            "nsfw": false,
            "spoiler": false,
            "author": "VegetableAd1108",
            "ups": 93
        },
        {
            "postLink": "https://redd.it/1epg0x3",
            "subreddit": "Discordmemes",
            "title": "beck x radiohead",
            "url": "https://i.redd.it/ouu7bxxtxzhd1.png",
            "nsfw": false,
            "spoiler": false,
            "author": "Help_Me1234567810",
            "ups": 24
        },
        {
            "postLink": "https://redd.it/1fpbczf",
            "subreddit": "Discordmemes",
            "title": "WHY \ud83d\ude2d",
            "url": "https://i.redd.it/iv739m7xyzqd1.jpeg",
            "nsfw": false,
            "spoiler": false,
            "author": "Beneficial_Trash9708",
            "ups": 31
        },
        {
            "postLink": "https://redd.it/1emvcpc",
            "subreddit": "Discordmemes",
            "title": "I've been seeing this everywhere so rizz me up",
            "url": "https://i.redd.it/v2vxkip8wchd1.png",
            "nsfw": false,
            "spoiler": false,
            "author": "TheButtTicklerbandit",
            "ups": 655
        },
        {
            "postLink": "https://redd.it/1f5qppg",
            "subreddit": "Discordmemes",
            "title": "This is the type of stuff i always have to see.",
            "url": "https://i.redd.it/8lpdum93w0md1.png",
            "nsfw": false,
            "spoiler": false,
            "author": "lollll7",
            "ups": 8
        },
        {
            "postLink": "https://redd.it/1f6tk88",
            "subreddit": "Discordmemes",
            "title": "Its Squashing time",
            "url": "https://i.redd.it/e9493pgajamd1.jpeg",
            "nsfw": false,
            "spoiler": false,
            "author": "RoGamer1014",
            "ups": 27
        },
        {
            "postLink": "https://redd.it/1ezyhkf",
            "subreddit": "Discordmemes",
            "title": "Mojang",
            "url": "https://i.redd.it/9qqa1sgezjkd1.jpeg",
            "nsfw": false,
            "spoiler": false,
            "author": "[deleted]",
            "ups": 7
        },
        {
            "postLink": "https://redd.it/1eveqq4",
            "subreddit": "Discordmemes",
            "title": "Sarcastic Interaction.",
            "url": "https://i.redd.it/26y5pfh1jgjd1.png",
            "nsfw": false,
            "spoiler": false,
            "author": "Frisk-256",
            "ups": 0
        },
        {
            "postLink": "https://redd.it/1fbp7y2",
            "subreddit": "Discordmemes",
            "title": "after this my homie got a lil mad",
            "url": "https://i.redd.it/2ky588gcfind1.png",
            "nsfw": false,
            "spoiler": false,
            "author": "CORMDOGGO",
            "ups": 73
        },
        {
            "postLink": "https://redd.it/1fmevnu",
            "subreddit": "Discordmemes",
            "title": "D-Bucks",
            "url": "https://i.redd.it/jgmtdn05q8qd1.png",
            "nsfw": false,
            "spoiler": false,
            "author": "YourPalLex",
            "ups": 7
        },
        {
            "postLink": "https://redd.it/1fxmhzq",
            "subreddit": "Discordmemes",
            "title": "stop",
            "url": "https://i.redd.it/j1wihpu6d6td1.png",
            "nsfw": false,
            "spoiler": false,
            "author": "Odd-Iron-6860",
            "ups": 125
        },
        {
            "postLink": "https://redd.it/1f9j1fl",
            "subreddit": "Discordmemes",
            "title": "Where's the rest of ya?",
            "url": "https://i.redd.it/ipyafwo8wymd1.jpeg",
            "nsfw": false,
            "spoiler": false,
            "author": "Embarrassed-Book7904",
            "ups": 26
        },
        {
            "postLink": "https://redd.it/1fkllka",
            "subreddit": "Discordmemes",
            "title": ".",
            "url": "https://i.redd.it/j0nk7onlvrpd1.jpeg",
            "nsfw": false,
            "spoiler": false,
            "author": "BarracudaJust4108",
            "ups": 134
        },
        {
            "postLink": "https://redd.it/1exscl6",
            "subreddit": "Discordmemes",
            "title": "Ah, how much I love being in a dsmp without the drama.",
            "url": "https://i.redd.it/sak12h19b1kd1.png",
            "nsfw": false,
            "spoiler": false,
            "author": "weapingwillowiam",
            "ups": 25
        },
        {
            "postLink": "https://redd.it/1fhstve",
            "subreddit": "Discordmemes",
            "title": "go on",
            "url": "https://i.redd.it/ovnbob5901pd1.jpeg",
            "nsfw": false,
            "spoiler": false,
            "author": "kevinjamesgapingass",
            "ups": 316
        },
        {
            "postLink": "https://redd.it/1f6tqig",
            "subreddit": "Discordmemes",
            "title": "A win is a win",
            "url": "https://i.redd.it/6yfaogtrkamd1.jpeg",
            "nsfw": false,
            "spoiler": false,
            "author": "FlashwingS3",
            "ups": 678
        },
        {
            "postLink": "https://redd.it/1fmbi4y",
            "subreddit": "Discordmemes",
            "title": "Pleading face.",
            "url": "https://i.redd.it/n26jnxxex7qd1.png",
            "nsfw": false,
            "spoiler": false,
            "author": "katiebug586",
            "ups": 29
        },
        {
            "postLink": "https://redd.it/1eslkos",
            "subreddit": "Discordmemes",
            "title": "Hmmm",
            "url": "https://i.redd.it/zjr198tl2rid1.png",
            "nsfw": false,
            "spoiler": false,
            "author": "FTTDLS",
            "ups": 14
        },
        {
            "postLink": "https://redd.it/1fakg9z",
            "subreddit": "Discordmemes",
            "title": "Dumbbells are the only thing I\u2019m holding",
            "url": "https://i.redd.it/80wdyvdzh3nd1.jpeg",
            "nsfw": false,
            "spoiler": false,
            "author": "Awkward_Salt_2588",
            "ups": 76
        },
        {
            "postLink": "https://redd.it/1fu7cab",
            "subreddit": "Discordmemes",
            "title": "Do it",
            "url": "https://i.redd.it/i2e3i2wlq2p71.gif",
            "nsfw": false,
            "spoiler": false,
            "author": "Several-Gear5474",
            "ups": 175
        },
        {
            "postLink": "https://redd.it/1f6t1e6",
            "subreddit": "Discordmemes",
            "title": "Please stand up",
            "url": "https://i.redd.it/ifvewrqleamd1.jpeg",
            "nsfw": false,
            "spoiler": false,
            "author": "TheGuyWhoAsked1014",
            "ups": 2333
        },
        {
            "postLink": "https://redd.it/1fcxt85",
            "subreddit": "Discordmemes",
            "title": "Simple yet effective",
            "url": "https://i.redd.it/34i398py2und1.jpeg",
            "nsfw": false,
            "spoiler": false,
            "author": "FlashwingS3",
            "ups": 288
        },
        {
            "postLink": "https://redd.it/1fi9sex",
            "subreddit": "Discordmemes",
            "title": "Well done..",
            "url": "https://i.redd.it/3uqoi08cc7pd1.png",
            "nsfw": false,
            "spoiler": false,
            "author": "ThDynamicGaming",
            "ups": 104
        },
        {
            "postLink": "https://redd.it/1fss01f",
            "subreddit": "Discordmemes",
            "title": "The world is mine to craft",
            "url": "https://i.redd.it/mikzv6dz7xrd1.jpeg",
            "nsfw": false,
            "spoiler": false,
            "author": "Mr_RogersInASweater",
            "ups": 321
        },
        {
            "postLink": "https://redd.it/1f4k49f",
            "subreddit": "Discordmemes",
            "title": "Gym meme",
            "url": "https://i.redd.it/3pqklmnfwold1.jpeg",
            "nsfw": false,
            "spoiler": false,
            "author": "Awkward_Salt_2588",
            "ups": 60
        },
        {
            "postLink": "https://redd.it/1fpzt45",
            "subreddit": "Discordmemes",
            "title": "Discord meme #5",
            "url": "https://i.redd.it/yaoorcdwf6rd1.jpeg",
            "nsfw": false,
            "spoiler": false,
            "author": "AleksKvas",
            "ups": 738
        },
        {
            "postLink": "https://redd.it/1esh4qp",
            "subreddit": "Discordmemes",
            "title": "Frog",
            "url": "https://i.redd.it/a224xhhb0qid1.jpeg",
            "nsfw": false,
            "spoiler": false,
            "author": "MyNameIsTheManiac",
            "ups": 26
        },
        {
            "postLink": "https://redd.it/1ep32up",
            "subreddit": "Discordmemes",
            "title": "try it, i dare you",
            "url": "https://i.redd.it/q50zpysggwhd1.jpeg",
            "nsfw": false,
            "spoiler": false,
            "author": "Nobody2928373",
            "ups": 496
        },
        {
            "postLink": "https://redd.it/1fd4l4w",
            "subreddit": "Discordmemes",
            "title": "nahh really",
            "url": "https://i.redd.it/tpw0syamivnd1.png",
            "nsfw": false,
            "spoiler": false,
            "author": "Much-Reindeer-2633",
            "ups": 384
        },
        {
            "postLink": "https://redd.it/1fgyu2s",
            "subreddit": "Discordmemes",
            "title": "They're fucked up",
            "url": "https://i.redd.it/72rdqrtuyuod1.png",
            "nsfw": false,
            "spoiler": false,
            "author": "Dry_Communication403",
            "ups": 21
        },
        {
            "postLink": "https://redd.it/1esydag",
            "subreddit": "Discordmemes",
            "title": "Never join ishowspeed discord\u2019s server",
            "url": "https://i.redd.it/tj4kul02luid1.jpeg",
            "nsfw": false,
            "spoiler": true,
            "author": "FickleMusician7590",
            "ups": 0
        },
        {
            "postLink": "https://redd.it/1ex4f3s",
            "subreddit": "Discordmemes",
            "title": "worst ways to torture someone: be the Garvey",
            "url": "https://i.redd.it/eihmj9h9dvjd1.png",
            "nsfw": false,
            "spoiler": false,
            "author": "Oystertheorangeotter",
            "ups": 30
        },
        {
            "postLink": "https://redd.it/1frxi0b",
            "subreddit": "Discordmemes",
            "title": "do i answer the dm? i think its important.",
            "url": "https://i.redd.it/pe1myrs3sord1.png",
            "nsfw": false,
            "spoiler": false,
            "author": "imreallybored2134",
            "ups": 32
        },
        {
            "postLink": "https://redd.it/1f4lyws",
            "subreddit": "Discordmemes",
            "title": "What do you mean \"This content is no longer available\"",
            "url": "https://i.redd.it/phwavncj4qld1.png",
            "nsfw": false,
            "spoiler": false,
            "author": "TNT_20202",
            "ups": 202
        },
        {
            "postLink": "https://redd.it/1ezt13p",
            "subreddit": "Discordmemes",
            "title": "Chad Steve ",
            "url": "https://i.redd.it/lndwt5yjgikd1.png",
            "nsfw": false,
            "spoiler": false,
            "author": "bb420backup",
            "ups": 131
        },
        {
            "postLink": "https://redd.it/1eso2mw",
            "subreddit": "Discordmemes",
            "title": "The duality of man",
            "url": "https://i.redd.it/whevca24trid1.jpeg",
            "nsfw": false,
            "spoiler": false,
            "author": "tomahawk7274",
            "ups": 57
        },
        {
            "postLink": "https://redd.it/1eoyyqw",
            "subreddit": "Discordmemes",
            "title": "Silly interaction in a private server.",
            "url": "https://i.redd.it/biurooyijvhd1.jpeg",
            "nsfw": true,
            "spoiler": false,
            "author": "Luh_CaIm_Fit",
            "ups": 23
        },
        {
            "postLink": "https://redd.it/1ezkd1f",
            "subreddit": "Discordmemes",
            "title": "Texas Seasons Guide",
            "url": "https://i.redd.it/z3sapphwkgkd1.jpeg",
            "nsfw": false,
            "spoiler": false,
            "author": "MyNameIsTheManiac",
            "ups": 134
        },
        {
            "postLink": "https://redd.it/1fi8gri",
            "subreddit": "Discordmemes",
            "title": "Win win scenario",
            "url": "https://i.redd.it/k6pakw6537pd1.jpeg",
            "nsfw": false,
            "spoiler": false,
            "author": "Awkward_Salt_2588",
            "ups": 596
        }
    ]
}