{
    "count": 100,
    "parental": [
        {
            "postLink": "https://redd.it/1ddlcik",
            "subreddit": "parentmemes",
            "title": "he wants some too",
            "url": "https://i.redd.it/cnvsvps6cw5d1.jpeg",
            "nsfw": false,
            "spoiler": false,
            "author": "RemarkableNatural107",
            "ups": 7
        },
        {
            "postLink": "https://redd.it/1dymlw6",
            "subreddit": "parentmemes",
            "title": "It's fractions for me\ud83d\ude1e\u270b\ud83c\udffe...",
            "url": "https://i.redd.it/j4efporzidbd1.png",
            "nsfw": false,
            "spoiler": false,
            "author": "B0omshaka",
            "ups": 3
        },
        {
            "postLink": "https://redd.it/1ak7dyu",
            "subreddit": "parentmemes",
            "title": "Boys vs girls",
            "url": "https://i.redd.it/amzlk6kp7ygc1.jpeg",
            "nsfw": false,
            "spoiler": false,
            "author": "Pumuckl4Life",
            "ups": 12
        },
        {
            "postLink": "https://redd.it/1d13hjg",
            "subreddit": "parentmemes",
            "title": "about to smack them kids",
            "url": "https://i.redd.it/a2ebx3jlwl2d1.jpeg",
            "nsfw": false,
            "spoiler": false,
            "author": "RemarkableNatural107",
            "ups": 9
        },
        {
            "postLink": "https://redd.it/1ffa5iz",
            "subreddit": "parentmemes",
            "title": "If it\u2019s not one thing, it\u2019s another \ud83d\ude02",
            "url": "https://i.redd.it/72zmm44dcfod1.jpeg",
            "nsfw": false,
            "spoiler": false,
            "author": "catladyscientist",
            "ups": 12
        },
        {
            "postLink": "https://redd.it/1f9b6ac",
            "subreddit": "parentmemes",
            "title": "Put on your own oxygen mask first!!!1",
            "url": "https://i.redd.it/ryby48n1fwmd1.gif",
            "nsfw": false,
            "spoiler": false,
            "author": "Smooth_Instruction11",
            "ups": 4
        },
        {
            "postLink": "https://redd.it/1b3304k",
            "subreddit": "parentmemes",
            "title": "That's one big door. ",
            "url": "https://i.redd.it/xkrxruy4mjlc1.png",
            "nsfw": false,
            "spoiler": false,
            "author": "FickleSeries9390",
            "ups": 8
        },
        {
            "postLink": "https://redd.it/12xz1l5",
            "subreddit": "parentmemes",
            "title": "Teenagers",
            "url": "https://i.redd.it/xj8ts8vqswva1.png",
            "nsfw": false,
            "spoiler": false,
            "author": "Weak_Desk_4992",
            "ups": 21
        },
        {
            "postLink": "https://redd.it/1bqtutt",
            "subreddit": "parentmemes",
            "title": "The amount of water bottles in the lost and found if the children\u2019s gymnastic place I\u2019m at",
            "url": "https://i.redd.it/pcn77lbd85rc1.jpeg",
            "nsfw": false,
            "spoiler": false,
            "author": "mason240",
            "ups": 5
        },
        {
            "postLink": "https://redd.it/y5vkwv",
            "subreddit": "parentmemes",
            "title": "The coveted surprise oat",
            "url": "https://i.redd.it/33ig90iy4oc81.jpg",
            "nsfw": false,
            "spoiler": false,
            "author": "MoonBapple",
            "ups": 15
        },
        {
            "postLink": "https://redd.it/17byyt9",
            "subreddit": "parentmemes",
            "title": "Holidays are hard",
            "url": "https://i.redd.it/um0vkk2dc9vb1.jpg",
            "nsfw": false,
            "spoiler": false,
            "author": "Bea_Stings",
            "ups": 12
        },
        {
            "postLink": "https://redd.it/18qi7j2",
            "subreddit": "parentmemes",
            "title": "Wtf why so many names",
            "url": "https://i.redd.it/10raslfcvf8c1.png",
            "nsfw": false,
            "spoiler": false,
            "author": "KingMimikyu09",
            "ups": 4
        },
        {
            "postLink": "https://redd.it/17lan7l",
            "subreddit": "parentmemes",
            "title": "Sacrifices are needed",
            "url": "https://i.imgur.com/ggmYV3E.jpg",
            "nsfw": false,
            "spoiler": false,
            "author": "SandiegoJack",
            "ups": 1
        },
        {
            "postLink": "https://redd.it/x7ux3d",
            "subreddit": "parentmemes",
            "title": "forgot the wash cloth",
            "url": "https://i.redd.it/ci3uuaq1iem91.jpg",
            "nsfw": false,
            "spoiler": false,
            "author": "vezzick",
            "ups": 18
        },
        {
            "postLink": "https://redd.it/xe5gvw",
            "subreddit": "parentmemes",
            "title": "yum",
            "url": "https://i.redd.it/ukqf1p1i0wn91.jpg",
            "nsfw": false,
            "spoiler": false,
            "author": "MoonBapple",
            "ups": 28
        },
        {
            "postLink": "https://redd.it/1c1d7yb",
            "subreddit": "parentmemes",
            "title": "Compliments to the chef \ud83e\udd0c\ud83c\udffc",
            "url": "https://i.redd.it/6ytw4y1vautc1.jpeg",
            "nsfw": false,
            "spoiler": false,
            "author": "coopalo0op",
            "ups": 9
        },
        {
            "postLink": "https://redd.it/xe5g11",
            "subreddit": "parentmemes",
            "title": "shamelessly stolen from r/spaceporn",
            "url": "https://i.redd.it/uje9qkia0wn91.png",
            "nsfw": false,
            "spoiler": false,
            "author": "MoonBapple",
            "ups": 10
        },
        {
            "postLink": "https://redd.it/1dtsret",
            "subreddit": "parentmemes",
            "title": "Pet sperm is not amused",
            "url": "https://i.redd.it/dp7qhue245ad1.jpeg",
            "nsfw": false,
            "spoiler": false,
            "author": "RemarkableNatural107",
            "ups": 0
        },
        {
            "postLink": "https://redd.it/12o1uxj",
            "subreddit": "parentmemes",
            "title": "oh god I think they heard me",
            "url": "https://i.redd.it/n6xkf4cxn7ua1.jpg",
            "nsfw": false,
            "spoiler": false,
            "author": "crummy",
            "ups": 34
        },
        {
            "postLink": "https://redd.it/1eljflo",
            "subreddit": "parentmemes",
            "title": "lol",
            "url": "https://i.redd.it/xap3ru2js1hd1.jpeg",
            "nsfw": false,
            "spoiler": false,
            "author": "RemarkableNatural107",
            "ups": 14
        },
        {
            "postLink": "https://redd.it/1ek1knz",
            "subreddit": "parentmemes",
            "title": "Moving with a Baby [OC]",
            "url": "https://i.redd.it/596alftg8ogd1.png",
            "nsfw": false,
            "spoiler": false,
            "author": "RemarkableNatural107",
            "ups": 5
        },
        {
            "postLink": "https://redd.it/1alf11a",
            "subreddit": "parentmemes",
            "title": "i'm no where near being a dad by blood but if i was:",
            "url": "https://i.redd.it/wb7w2deck8hc1.png",
            "nsfw": false,
            "spoiler": false,
            "author": "SnooStrawberries795",
            "ups": 10
        },
        {
            "postLink": "https://redd.it/yy34jq",
            "subreddit": "parentmemes",
            "title": "An abundance of love and caution",
            "url": "https://i.redd.it/noy0q4qtlm0a1.png",
            "nsfw": false,
            "spoiler": false,
            "author": "MoonBapple",
            "ups": 11
        },
        {
            "postLink": "https://redd.it/xhohjr",
            "subreddit": "parentmemes",
            "title": "The mystery continues",
            "url": "https://i.redd.it/9mevcrqwnno91.jpg",
            "nsfw": false,
            "spoiler": false,
            "author": "MoonBapple",
            "ups": 17
        },
        {
            "postLink": "https://redd.it/16dreuj",
            "subreddit": "parentmemes",
            "title": "The struggle",
            "url": "https://i.redd.it/uaipoya7l4nb1.jpg",
            "nsfw": false,
            "spoiler": false,
            "author": "madorwhatever",
            "ups": 10
        },
        {
            "postLink": "https://redd.it/1du3a7x",
            "subreddit": "parentmemes",
            "title": "Applying for work like ",
            "url": "https://i.redd.it/pssneyz401ad1.jpeg",
            "nsfw": false,
            "spoiler": false,
            "author": "MoonBapple",
            "ups": 3
        },
        {
            "postLink": "https://redd.it/179n5wj",
            "subreddit": "parentmemes",
            "title": "What\u2019s that?",
            "url": "https://i.redd.it/qbf09gm56oub1.jpg",
            "nsfw": false,
            "spoiler": false,
            "author": "Funaussiecouplex",
            "ups": 23
        },
        {
            "postLink": "https://redd.it/18d8oao",
            "subreddit": "parentmemes",
            "title": "There is no peace",
            "url": "https://i.redd.it/q0537im1iy4c1.jpg",
            "nsfw": false,
            "spoiler": false,
            "author": "J_Valente",
            "ups": 15
        },
        {
            "postLink": "https://redd.it/179n66x",
            "subreddit": "parentmemes",
            "title": "Couldn\u2019t relate more",
            "url": "https://i.redd.it/c48wiay76oub1.jpg",
            "nsfw": false,
            "spoiler": false,
            "author": "Funaussiecouplex",
            "ups": 25
        },
        {
            "postLink": "https://redd.it/17088g1",
            "subreddit": "parentmemes",
            "title": "So true lmao",
            "url": "https://i.redd.it/ep3a99g56bsb1.jpg",
            "nsfw": false,
            "spoiler": false,
            "author": "ToughlyRun72",
            "ups": 6
        },
        {
            "postLink": "https://redd.it/188tpno",
            "subreddit": "parentmemes",
            "title": "It's a delicate procedure",
            "url": "https://i.redd.it/3hw54cnzos3c1.jpg",
            "nsfw": false,
            "spoiler": false,
            "author": "TheRealOcsiban",
            "ups": 11
        },
        {
            "postLink": "https://redd.it/1ffb2x3",
            "subreddit": "parentmemes",
            "title": "Ain\u2019t it the truth ",
            "url": "https://i.redd.it/tw6oh1iajfod1.jpeg",
            "nsfw": true,
            "spoiler": false,
            "author": "treylanford",
            "ups": 21
        },
        {
            "postLink": "https://redd.it/ysbex0",
            "subreddit": "parentmemes",
            "title": "So this is toddlerhood",
            "url": "https://i.redd.it/isripygbo6z91.jpg",
            "nsfw": false,
            "spoiler": false,
            "author": "mason240",
            "ups": 13
        },
        {
            "postLink": "https://redd.it/1fne4x8",
            "subreddit": "parentmemes",
            "title": "solid!",
            "url": "https://i.redd.it/4ew05pccqhqd1.jpeg",
            "nsfw": false,
            "spoiler": false,
            "author": "RemarkableNatural107",
            "ups": 16
        },
        {
            "postLink": "https://redd.it/xe5hmy",
            "subreddit": "parentmemes",
            "title": "Bedtime =/= Sleep Time",
            "url": "https://i.redd.it/mu5ovpdn0wn91.jpg",
            "nsfw": false,
            "spoiler": false,
            "author": "MoonBapple",
            "ups": 12
        },
        {
            "postLink": "https://redd.it/1dvuy2p",
            "subreddit": "parentmemes",
            "title": "truly uncanny",
            "url": "https://i.redd.it/lbkn9noxhoad1.jpeg",
            "nsfw": false,
            "spoiler": false,
            "author": "crummy",
            "ups": 11
        },
        {
            "postLink": "https://redd.it/1dh3fa9",
            "subreddit": "parentmemes",
            "title": "Still hurts years later \ud83d\ude2b",
            "url": "https://i.redd.it/7f323cwydw6d1.jpeg",
            "nsfw": false,
            "spoiler": false,
            "author": "HurryingBog3049",
            "ups": 15
        },
        {
            "postLink": "https://redd.it/154g0at",
            "subreddit": "parentmemes",
            "title": "Every. Night.",
            "url": "https://i.redd.it/vki3b3qlk1db1.jpg",
            "nsfw": false,
            "spoiler": false,
            "author": "manin_highcastle62",
            "ups": 15
        },
        {
            "postLink": "https://redd.it/xkgto8",
            "subreddit": "parentmemes",
            "title": "Being honest w/ my kids",
            "url": "https://i.redd.it/t82ulan10ap91.jpg",
            "nsfw": false,
            "spoiler": false,
            "author": "Mad_Marrragan",
            "ups": 9
        },
        {
            "postLink": "https://redd.it/xgdymi",
            "subreddit": "parentmemes",
            "title": "Once upon a contact nap...",
            "url": "https://i.redd.it/wdiynr09deo91.jpg",
            "nsfw": false,
            "spoiler": false,
            "author": "MoonBapple",
            "ups": 7
        },
        {
            "postLink": "https://redd.it/xgddew",
            "subreddit": "parentmemes",
            "title": "She's really digesting the material...",
            "url": "https://i.redd.it/blt139tx8eo91.jpg",
            "nsfw": false,
            "spoiler": false,
            "author": "MoonBapple",
            "ups": 15
        },
        {
            "postLink": "https://redd.it/15xo4ma",
            "subreddit": "parentmemes",
            "title": "I mean I'm not perfect but I'm better than them",
            "url": "https://i.redd.it/n5ey4r40ujjb1.png",
            "nsfw": false,
            "spoiler": false,
            "author": "Accurate_Dirt5794",
            "ups": 5
        },
        {
            "postLink": "https://redd.it/1686rbn",
            "subreddit": "parentmemes",
            "title": "Bedtime Vibes",
            "url": "https://i.redd.it/03t9l4qkaplb1.png",
            "nsfw": false,
            "spoiler": false,
            "author": "MoonBapple",
            "ups": 16
        },
        {
            "postLink": "https://redd.it/z4qcjj",
            "subreddit": "parentmemes",
            "title": "The shorter they are, the less intelligible",
            "url": "https://i.redd.it/4o2nf5r0062a1.jpg",
            "nsfw": false,
            "spoiler": false,
            "author": "Magical__Fetus",
            "ups": 21
        },
        {
            "postLink": "https://redd.it/1exeeaq",
            "subreddit": "parentmemes",
            "title": "Pls stop fighting me \ud83d\ude2d",
            "url": "https://i.redd.it/822askiqixjd1.jpeg",
            "nsfw": false,
            "spoiler": false,
            "author": "sail0r_m3rcury",
            "ups": 11
        },
        {
            "postLink": "https://redd.it/13i44v8",
            "subreddit": "parentmemes",
            "title": "Wise words fr(o)m a s(c)holar and educator.",
            "url": "https://i.redd.it/q2i6806li00b1.jpg",
            "nsfw": false,
            "spoiler": false,
            "author": "TommyJaimeBass",
            "ups": 7
        },
        {
            "postLink": "https://redd.it/1exelxx",
            "subreddit": "parentmemes",
            "title": "\ud83e\udd2b",
            "url": "https://i.redd.it/d3obi0kjkxjd1.jpeg",
            "nsfw": false,
            "spoiler": false,
            "author": "Hi_Im_Chantelle",
            "ups": 17
        },
        {
            "postLink": "https://redd.it/14yls9j",
            "subreddit": "parentmemes",
            "title": "Paw Patrol Movie From A Parent Persoective",
            "url": "https://i.redd.it/g3o0ksmjoqbb1.jpg",
            "nsfw": false,
            "spoiler": false,
            "author": "Wmoot599",
            "ups": 7
        },
        {
            "postLink": "https://redd.it/1e2766w",
            "subreddit": "parentmemes",
            "title": "I\u2019ll never understand this",
            "url": "https://i.redd.it/a8d04bb2c4cd1.jpeg",
            "nsfw": false,
            "spoiler": false,
            "author": "RemarkableNatural107",
            "ups": 9
        },
        {
            "postLink": "https://redd.it/1emc6iq",
            "subreddit": "parentmemes",
            "title": "Career Path Unlocked: Learn about dinosaurs while jumping on trampoline",
            "url": "https://i.redd.it/idf6kzjax8hd1.png",
            "nsfw": false,
            "spoiler": false,
            "author": "XzaltedEmpire",
            "ups": 6
        },
        {
            "postLink": "https://redd.it/1f6wh2h",
            "subreddit": "parentmemes",
            "title": "My toddler about to blow my argument out of the water for the 60th time today.",
            "url": "https://i.redd.it/p2fr7wiaabmd1.jpeg",
            "nsfw": false,
            "spoiler": false,
            "author": "Solarpowered-Couch",
            "ups": 13
        },
        {
            "postLink": "https://redd.it/x07rrg",
            "subreddit": "parentmemes",
            "title": "IYKYK",
            "url": "https://i.imgur.com/mFyOG43.jpg",
            "nsfw": true,
            "spoiler": false,
            "author": "larryb78",
            "ups": 25
        },
        {
            "postLink": "https://redd.it/xxi5uc",
            "subreddit": "parentmemes",
            "title": "\ud83e\udeb5 \ud83d\udc27",
            "url": "https://i.redd.it/eitvlfsvd7s91.jpg",
            "nsfw": false,
            "spoiler": false,
            "author": "MoonBapple",
            "ups": 11
        },
        {
            "postLink": "https://redd.it/10fd11a",
            "subreddit": "parentmemes",
            "title": "yes",
            "url": "https://i.redd.it/g4k230326uca1.png",
            "nsfw": false,
            "spoiler": false,
            "author": "Landmannalaugar_0_0",
            "ups": 39
        },
        {
            "postLink": "https://redd.it/172lhgu",
            "subreddit": "parentmemes",
            "title": "I\u2019ll miss that song. IYKYK",
            "url": "https://i.redd.it/eol9w2ooivsb1.jpg",
            "nsfw": false,
            "spoiler": false,
            "author": "rickard91",
            "ups": 10
        },
        {
            "postLink": "https://redd.it/110vj0d",
            "subreddit": "parentmemes",
            "title": "it's true",
            "url": "https://i.redd.it/o00iykqbdwha1.jpg",
            "nsfw": false,
            "spoiler": false,
            "author": "ThePremiumSniper",
            "ups": 5
        },
        {
            "postLink": "https://redd.it/zhgm6d",
            "subreddit": "parentmemes",
            "title": "my pregnant wife wouldn't let this be our baby announcement so I'm posting it here",
            "url": "https://i.redd.it/h0h5x8hvfz4a1.jpg",
            "nsfw": false,
            "spoiler": false,
            "author": "MoonBapple",
            "ups": 30
        },
        {
            "postLink": "https://redd.it/13yvq0x",
            "subreddit": "parentmemes",
            "title": "\ud83d\ude08",
            "url": "https://i.redd.it/2pjchj6odp3b1.jpg",
            "nsfw": false,
            "spoiler": false,
            "author": "[deleted]",
            "ups": 9
        },
        {
            "postLink": "https://redd.it/1andn1u",
            "subreddit": "parentmemes",
            "title": "Every time",
            "url": "https://i.redd.it/zjgh0f11mqhc1.jpeg",
            "nsfw": false,
            "spoiler": false,
            "author": "fambestera",
            "ups": 20
        },
        {
            "postLink": "https://redd.it/1f7j5du",
            "subreddit": "parentmemes",
            "title": "Toddler owned the jury with this killer filibuster.",
            "url": "https://i.redd.it/hdxd5adswgmd1.jpeg",
            "nsfw": false,
            "spoiler": false,
            "author": "Solarpowered-Couch",
            "ups": 12
        },
        {
            "postLink": "https://redd.it/z5jsx3",
            "subreddit": "parentmemes",
            "title": "Task initiation.",
            "url": "https://i.imgur.com/1WGrRl1.jpg",
            "nsfw": false,
            "spoiler": false,
            "author": "MoonBapple",
            "ups": 18
        },
        {
            "postLink": "https://redd.it/141ggxr",
            "subreddit": "parentmemes",
            "title": "Ask not to have emotional meltdowns...",
            "url": "https://i.redd.it/nb545vwcp54b1.png",
            "nsfw": false,
            "spoiler": false,
            "author": "MoonBapple",
            "ups": 6
        },
        {
            "postLink": "https://redd.it/1dnw7z8",
            "subreddit": "parentmemes",
            "title": "Music to my ears",
            "url": "https://i.redd.it/unkf4iqlym8d1.jpeg",
            "nsfw": false,
            "spoiler": false,
            "author": "watevauwant",
            "ups": 7
        },
        {
            "postLink": "https://redd.it/16ty576",
            "subreddit": "parentmemes",
            "title": "Be grateful for all you have, even kids your teens that drive you nuts sometimes! \ud83e\udd2a Hope this helps keep a smile on your face \ud83e\udd29 \u2014 More at curlystache.com",
            "url": "https://i.redd.it/v34sjcvxivqb1.jpg",
            "nsfw": false,
            "spoiler": false,
            "author": "CurlyStacheBlog",
            "ups": 0
        },
        {
            "postLink": "https://redd.it/1d6i2yu",
            "subreddit": "parentmemes",
            "title": "Trying to learn some cute songs to sing our first born and WTF",
            "url": "https://i.redd.it/wtcw6spcy64d1.jpeg",
            "nsfw": false,
            "spoiler": false,
            "author": "Fuzzy_Straitjacket",
            "ups": 19
        },
        {
            "postLink": "https://redd.it/zolus6",
            "subreddit": "parentmemes",
            "title": "2meirl4meirl",
            "url": "https://i.redd.it/n23btac52e6a1.jpg",
            "nsfw": false,
            "spoiler": false,
            "author": "MoonBapple",
            "ups": 12
        },
        {
            "postLink": "https://redd.it/13elcq4",
            "subreddit": "parentmemes",
            "title": "Nighttime with newborn twins as a FTP",
            "url": "https://i.imgur.com/ynoPCkC.jpg",
            "nsfw": false,
            "spoiler": false,
            "author": "sharkbait_oohaha",
            "ups": 16
        },
        {
            "postLink": "https://redd.it/16zmm2s",
            "subreddit": "parentmemes",
            "title": "Teaching my kid to read when he pretends he can't.",
            "url": "https://i.redd.it/6fzl1jupo6sb1.png",
            "nsfw": false,
            "spoiler": false,
            "author": "HooptyDooDooMeister",
            "ups": 13
        },
        {
            "postLink": "https://redd.it/xu1iqy",
            "subreddit": "parentmemes",
            "title": "Damn Right!",
            "url": "https://i.redd.it/1dnhyssmvgr91.jpg",
            "nsfw": false,
            "spoiler": false,
            "author": "MoonBapple",
            "ups": 15
        },
        {
            "postLink": "https://redd.it/1dx9rjw",
            "subreddit": "parentmemes",
            "title": "Congratulate my wife",
            "url": "https://i.redd.it/y329k61smxad1.jpeg",
            "nsfw": false,
            "spoiler": false,
            "author": "RemarkableNatural107",
            "ups": 5
        },
        {
            "postLink": "https://redd.it/xhqnzu",
            "subreddit": "parentmemes",
            "title": "[OC] They don't know...",
            "url": "https://i.redd.it/3h0ij1avtpo91.jpg",
            "nsfw": false,
            "spoiler": false,
            "author": "MoonBapple",
            "ups": 6
        },
        {
            "postLink": "https://redd.it/16v50rk",
            "subreddit": "parentmemes",
            "title": "Title",
            "url": "https://i.redd.it/1gzmxo8zc5rb1.jpg",
            "nsfw": false,
            "spoiler": false,
            "author": "Cornes",
            "ups": 3
        },
        {
            "postLink": "https://redd.it/1adz2kz",
            "subreddit": "parentmemes",
            "title": "Cardboard wins everytime.",
            "url": "https://i.redd.it/cyedpjuk0bfc1.jpeg",
            "nsfw": false,
            "spoiler": false,
            "author": "RemarkableNatural107",
            "ups": 14
        },
        {
            "postLink": "https://redd.it/1eizv61",
            "subreddit": "parentmemes",
            "title": "Are you okay after that?",
            "url": "https://i.redd.it/ghw62458vegd1.jpeg",
            "nsfw": false,
            "spoiler": false,
            "author": "RemarkableNatural107",
            "ups": 1
        },
        {
            "postLink": "https://redd.it/1csoxh0",
            "subreddit": "parentmemes",
            "title": "Energy vampires",
            "url": "https://i.redd.it/x7keq7j89m0d1.jpeg",
            "nsfw": false,
            "spoiler": false,
            "author": "RemarkableNatural107",
            "ups": 13
        },
        {
            "postLink": "https://redd.it/16v52dk",
            "subreddit": "parentmemes",
            "title": "Title",
            "url": "https://i.redd.it/xbayyutfd5rb1.jpg",
            "nsfw": false,
            "spoiler": false,
            "author": "Cornes",
            "ups": 18
        },
        {
            "postLink": "https://redd.it/z6iebj",
            "subreddit": "parentmemes",
            "title": "Made this after my daughter was born.",
            "url": "https://i.redd.it/1viw9l7lcl2a1.png",
            "nsfw": false,
            "spoiler": false,
            "author": "Putrid_Cod_5893",
            "ups": 19
        },
        {
            "postLink": "https://redd.it/xu1i8n",
            "subreddit": "parentmemes",
            "title": "\ud83d\udca4\ud83d\udc76\u23f0",
            "url": "https://i.redd.it/z4v04sthvgr91.jpg",
            "nsfw": false,
            "spoiler": false,
            "author": "MoonBapple",
            "ups": 30
        },
        {
            "postLink": "https://redd.it/14fnbbf",
            "subreddit": "parentmemes",
            "title": "Indeed",
            "url": "https://i.redd.it/3bh1znjsjg7b1.png",
            "nsfw": false,
            "spoiler": false,
            "author": "literallyeveryfandom",
            "ups": 10
        },
        {
            "postLink": "https://redd.it/14jbb8o",
            "subreddit": "parentmemes",
            "title": "Truth has been spoken",
            "url": "https://i.redd.it/xvnxoo7xuj7b1.jpg",
            "nsfw": false,
            "spoiler": false,
            "author": "MakeMeRichIDC",
            "ups": 9
        },
        {
            "postLink": "https://redd.it/xpey3i",
            "subreddit": "parentmemes",
            "title": "Titty = Snooze Button",
            "url": "https://i.redd.it/ukv9d54k6eq91.jpg",
            "nsfw": false,
            "spoiler": false,
            "author": "MoonBapple",
            "ups": 20
        },
        {
            "postLink": "https://redd.it/1eiguzu",
            "subreddit": "parentmemes",
            "title": "\"I'm not gunna hit you :)\" *wham*",
            "url": "https://i.redd.it/0fmhn1pbjagd1.gif",
            "nsfw": false,
            "spoiler": false,
            "author": "ForgottenPlayThing",
            "ups": 0
        },
        {
            "postLink": "https://redd.it/1dymmgc",
            "subreddit": "parentmemes",
            "title": "Not on my watch \ud83d\udc41\ufe0f\ud83d\udc41\ufe0f...",
            "url": "https://i.redd.it/a2rvsuo3jdbd1.png",
            "nsfw": false,
            "spoiler": false,
            "author": "B0omshaka",
            "ups": 0
        },
        {
            "postLink": "https://redd.it/14kiyds",
            "subreddit": "parentmemes",
            "title": "Bruno walks in with a mischievous grin",
            "url": "https://i.redd.it/6wv5qoz2cl8b1.jpg",
            "nsfw": false,
            "spoiler": false,
            "author": "Old_Knowledge_5988",
            "ups": 18
        },
        {
            "postLink": "https://redd.it/xe5q1j",
            "subreddit": "parentmemes",
            "title": "dispensing wisdom",
            "url": "https://i.redd.it/1osmq00a2wn91.png",
            "nsfw": false,
            "spoiler": false,
            "author": "MoonBapple",
            "ups": 16
        },
        {
            "postLink": "https://redd.it/11ntv2d",
            "subreddit": "parentmemes",
            "title": "Toddlers = Jackass",
            "url": "https://i.redd.it/ijyw271vvxma1.jpg",
            "nsfw": false,
            "spoiler": false,
            "author": "tim829",
            "ups": 30
        },
        {
            "postLink": "https://redd.it/10fhp3b",
            "subreddit": "parentmemes",
            "title": "i just want to sit down for a moment",
            "url": "https://i.redd.it/kqirwe8g2vca1.jpg",
            "nsfw": false,
            "spoiler": false,
            "author": "crummy",
            "ups": 27
        },
        {
            "postLink": "https://redd.it/10pfzs1",
            "subreddit": "parentmemes",
            "title": "Helpful dads be like",
            "url": "https://i.redd.it/tza2bmltrafa1.jpg",
            "nsfw": false,
            "spoiler": false,
            "author": "drtij_dzienz",
            "ups": 10
        },
        {
            "postLink": "https://redd.it/w0thit",
            "subreddit": "parentmemes",
            "title": "Jokes on them, I\u2019m taking it",
            "url": "https://i.redd.it/2311ms7nm0c91.jpg",
            "nsfw": false,
            "spoiler": false,
            "author": "Mad_Marrragan",
            "ups": 10
        },
        {
            "postLink": "https://redd.it/w5q29k",
            "subreddit": "parentmemes",
            "title": "Ummm ... sunflowers",
            "url": "https://i.redd.it/mg0jcgaeq7d91.png",
            "nsfw": true,
            "spoiler": false,
            "author": "sexywheat",
            "ups": 12
        },
        {
            "postLink": "https://redd.it/14kd6hk",
            "subreddit": "parentmemes",
            "title": "That feeling when the stuffed toy that a relative gifted, and you don\u2019t have a spare of, becomes the new favourite",
            "url": "https://i.redd.it/6ujbl18u6k8b1.jpg",
            "nsfw": false,
            "spoiler": false,
            "author": "Catlovercaity",
            "ups": 8
        },
        {
            "postLink": "https://redd.it/wocs21",
            "subreddit": "parentmemes",
            "title": "\"But I'm hungry\"",
            "url": "https://i.redd.it/p5dj9wbqzph91.png",
            "nsfw": false,
            "spoiler": false,
            "author": "sn0skier",
            "ups": 20
        },
        {
            "postLink": "https://redd.it/ysz4rw",
            "subreddit": "parentmemes",
            "title": "I'm not *just* a SAHP",
            "url": "https://i.redd.it/67tvrqz3zez91.jpg",
            "nsfw": false,
            "spoiler": false,
            "author": "MoonBapple",
            "ups": 22
        },
        {
            "postLink": "https://redd.it/13eqdab",
            "subreddit": "parentmemes",
            "title": "Fifth time's the charm!",
            "url": "https://i.redd.it/botv1gcoy7za1.jpg",
            "nsfw": false,
            "spoiler": false,
            "author": "jodudeit",
            "ups": 16
        },
        {
            "postLink": "https://redd.it/xhoid8",
            "subreddit": "parentmemes",
            "title": "Snack \ud83d\udc0d",
            "url": "https://i.redd.it/vqn7xtb92jo91.jpg",
            "nsfw": false,
            "spoiler": false,
            "author": "MoonBapple",
            "ups": 13
        },
        {
            "postLink": "https://redd.it/xi30y2",
            "subreddit": "parentmemes",
            "title": "\ud83e\udd80\ud83c\udf93",
            "url": "https://i.redd.it/t90iom0uepo91.jpg",
            "nsfw": false,
            "spoiler": false,
            "author": "MoonBapple",
            "ups": 14
        },
        {
            "postLink": "https://redd.it/yuuiio",
            "subreddit": "parentmemes",
            "title": "Time for xmas presents",
            "url": "https://i.redd.it/n41rz2qhkxz91.jpg",
            "nsfw": false,
            "spoiler": false,
            "author": "buckte",
            "ups": 2
        },
        {
            "postLink": "https://redd.it/135xne5",
            "subreddit": "parentmemes",
            "title": "Organic advertising :)",
            "url": "https://i.redd.it/d8qh0sjvhgxa1.jpg",
            "nsfw": false,
            "spoiler": false,
            "author": "MoonBapple",
            "ups": 24
        },
        {
            "postLink": "https://redd.it/102udg8",
            "subreddit": "parentmemes",
            "title": "\ud83e\udd26\u200d\u2642\ufe0f",
            "url": "https://i.redd.it/2gegi2q210aa1.jpg",
            "nsfw": false,
            "spoiler": false,
            "author": "StoneAgeRadio13",
            "ups": 4
        },
        {
            "postLink": "https://redd.it/198kdt7",
            "subreddit": "parentmemes",
            "title": "Perfectly timed noisy poops",
            "url": "https://i.redd.it/4tlft0swmwcc1.jpeg",
            "nsfw": false,
            "spoiler": false,
            "author": "TerrorTroodon",
            "ups": 18
        }
    ]
}