{
    "count": 100,
    "memes": [
        {
            "postLink": "https://redd.it/1g1hyvc",
            "subreddit": "sciencememes",
            "title": "Physicists",
            "url": "https://i.redd.it/73op0e25i6ud1.jpeg",
            "nsfw": false,
            "spoiler": false,
            "author": "developed_corey5559",
            "ups": 12
        },
        {
            "postLink": "https://redd.it/1g0klva",
            "subreddit": "sciencememes",
            "title": "It's just a movie",
            "url": "https://i.redd.it/9ribflfkzxtd1.jpeg",
            "nsfw": false,
            "spoiler": false,
            "author": "ecups2202",
            "ups": 460
        },
        {
            "postLink": "https://redd.it/1g13xw0",
            "subreddit": "sciencememes",
            "title": "oh yes",
            "url": "https://i.redd.it/biheze0us2ud1.png",
            "nsfw": false,
            "spoiler": false,
            "author": "sunkisseddarling",
            "ups": 6464
        },
        {
            "postLink": "https://redd.it/1g1wx0l",
            "subreddit": "sciencememes",
            "title": "Unlimited Powerrrrrrrr",
            "url": "https://i.redd.it/26quvpknuaud1.png",
            "nsfw": false,
            "spoiler": false,
            "author": "Savings_Client_5881",
            "ups": 124
        },
        {
            "postLink": "https://redd.it/1g16ysk",
            "subreddit": "sciencememes",
            "title": "Math, my favourite subject",
            "url": "https://i.redd.it/k9h2znbpx3ud1.png",
            "nsfw": false,
            "spoiler": false,
            "author": "lovelykaykayy",
            "ups": 27
        },
        {
            "postLink": "https://redd.it/1g1o7qm",
            "subreddit": "sciencememes",
            "title": "what is 2)",
            "url": "https://i.redd.it/dfuge891z7ud1.jpeg",
            "nsfw": false,
            "spoiler": false,
            "author": "petitefelicle9299",
            "ups": 19
        },
        {
            "postLink": "https://redd.it/1g13r5j",
            "subreddit": "sciencememes",
            "title": "Real     ",
            "url": "https://i.redd.it/9zgnyojzm2ud1.png",
            "nsfw": false,
            "spoiler": false,
            "author": "Reasonable_Moose_755",
            "ups": 40
        },
        {
            "postLink": "https://redd.it/1g17zhy",
            "subreddit": "sciencememes",
            "title": "Handle with care - I'm like a little salty bomb in your soup",
            "url": "https://i.redd.it/16w0e4kx84ud1.jpeg",
            "nsfw": false,
            "spoiler": false,
            "author": "Suitable-Salary8536",
            "ups": 35
        },
        {
            "postLink": "https://redd.it/1g1uwly",
            "subreddit": "sciencememes",
            "title": "Earthlike planets",
            "url": "https://i.redd.it/ytzzs26h2aud1.jpeg",
            "nsfw": false,
            "spoiler": false,
            "author": "chloemarini",
            "ups": 516
        },
        {
            "postLink": "https://redd.it/1g14dno",
            "subreddit": "sciencememes",
            "title": "The joy of chemistry",
            "url": "https://i.redd.it/1t3ox0lwy2ud1.png",
            "nsfw": false,
            "spoiler": false,
            "author": "fabuloussophie",
            "ups": 16
        },
        {
            "postLink": "https://redd.it/1g0gp6y",
            "subreddit": "sciencememes",
            "title": "I UNDERSTOOD THAT REFERANCE.",
            "url": "https://i.redd.it/s007zsph0xtd1.jpeg",
            "nsfw": false,
            "spoiler": false,
            "author": "YourFavLollipop",
            "ups": 1278
        },
        {
            "postLink": "https://redd.it/1g1gm14",
            "subreddit": "sciencememes",
            "title": "kek",
            "url": "https://i.redd.it/vredrh9b56ud1.jpeg",
            "nsfw": false,
            "spoiler": false,
            "author": "Sun10122",
            "ups": 26
        },
        {
            "postLink": "https://redd.it/1g1q95u",
            "subreddit": "sciencememes",
            "title": "They did Rosalind Franklin dirty and she shouldn't be reduced to a footnote in the history of DNA research.",
            "url": "https://i.redd.it/xf3oxd9ej8ud1.jpeg",
            "nsfw": false,
            "spoiler": false,
            "author": "blondearlyn7983",
            "ups": 0
        },
        {
            "postLink": "https://redd.it/1g0jsi4",
            "subreddit": "sciencememes",
            "title": "When chemistry class becomes a get-rich-quick scheme.",
            "url": "https://i.redd.it/72bztshvsxtd1.jpeg",
            "nsfw": false,
            "spoiler": false,
            "author": "CinderellaBliss",
            "ups": 150
        },
        {
            "postLink": "https://redd.it/1g1uw8c",
            "subreddit": "sciencememes",
            "title": "dreams",
            "url": "https://i.redd.it/p0pmenrb2aud1.png",
            "nsfw": false,
            "spoiler": false,
            "author": "sassydollyyy",
            "ups": 46
        },
        {
            "postLink": "https://redd.it/1g0n3g9",
            "subreddit": "sciencememes",
            "title": "A math meme",
            "url": "https://i.redd.it/781vlxwtiytd1.jpeg",
            "nsfw": false,
            "spoiler": false,
            "author": "angelamilfie8887",
            "ups": 4386
        },
        {
            "postLink": "https://redd.it/1g1qaqs",
            "subreddit": "sciencememes",
            "title": "Big explosions sell better than outpourings of lava.",
            "url": "https://i.redd.it/u3qpm4yyj8ud1.jpeg",
            "nsfw": false,
            "spoiler": false,
            "author": "Belkan-Federation95",
            "ups": 0
        },
        {
            "postLink": "https://redd.it/1g1o9qq",
            "subreddit": "sciencememes",
            "title": "impressive fact",
            "url": "https://i.redd.it/p4wxye1lz7ud1.jpeg",
            "nsfw": false,
            "spoiler": false,
            "author": "Kelly_XDream",
            "ups": 278
        },
        {
            "postLink": "https://redd.it/1g1hukt",
            "subreddit": "sciencememes",
            "title": "Evil Physicist",
            "url": "https://i.redd.it/xic4y4j4h6ud1.jpeg",
            "nsfw": false,
            "spoiler": false,
            "author": "cleanbebe2398",
            "ups": 19
        },
        {
            "postLink": "https://redd.it/1g174co",
            "subreddit": "sciencememes",
            "title": "She followed instructions, just not in the way you expected",
            "url": "https://i.redd.it/l0rqyawdz3ud1.jpeg",
            "nsfw": false,
            "spoiler": false,
            "author": "FloraWhisperGurly",
            "ups": 1720
        },
        {
            "postLink": "https://redd.it/1g0c3wh",
            "subreddit": "sciencememes",
            "title": "Remember when old sci-fi predicted we'd be colonizing the galaxy by 2003?\ud83d\ude02",
            "url": "https://i.redd.it/d2cquoerbvtd1.png",
            "nsfw": false,
            "spoiler": false,
            "author": "CurvyAngel55",
            "ups": 4338
        },
        {
            "postLink": "https://redd.it/1g19eyl",
            "subreddit": "sciencememes",
            "title": "suprise them!",
            "url": "https://i.redd.it/amdrcznim4ud1.jpeg",
            "nsfw": false,
            "spoiler": false,
            "author": "Schumi_visor",
            "ups": 88
        },
        {
            "postLink": "https://redd.it/1g0zvka",
            "subreddit": "sciencememes",
            "title": "earth is the largest rocky planet and the planet your pointing at is mars the one next to mars is earth.",
            "url": "https://i.redd.it/w5itc7b4i1ud1.jpeg",
            "nsfw": false,
            "spoiler": false,
            "author": "HotttiePie",
            "ups": 55
        },
        {
            "postLink": "https://redd.it/1g1dhpk",
            "subreddit": "sciencememes",
            "title": "can't",
            "url": "https://i.redd.it/uslanvzwg5ud1.jpeg",
            "nsfw": false,
            "spoiler": false,
            "author": "Shock7307",
            "ups": 8
        },
        {
            "postLink": "https://redd.it/1g1uu9x",
            "subreddit": "sciencememes",
            "title": "The body has been waiting for this day for a long time",
            "url": "https://i.redd.it/9bud8yxl1aud1.jpeg",
            "nsfw": false,
            "spoiler": false,
            "author": "msguiltypleasures",
            "ups": 11
        },
        {
            "postLink": "https://redd.it/1g0rlxz",
            "subreddit": "sciencememes",
            "title": "Too accurate",
            "url": "https://i.redd.it/5f1vz2u0iztd1.jpeg",
            "nsfw": false,
            "spoiler": false,
            "author": "existential_girl",
            "ups": 51
        },
        {
            "postLink": "https://redd.it/1g1qxyr",
            "subreddit": "sciencememes",
            "title": "I was like HOOOOOOOOOW",
            "url": "https://i.redd.it/p8tkdgunq8ud1.png",
            "nsfw": false,
            "spoiler": false,
            "author": "kitty_loove__",
            "ups": 563
        },
        {
            "postLink": "https://redd.it/1g1pku9",
            "subreddit": "sciencememes",
            "title": "omg",
            "url": "https://i.redd.it/p2wgqyjmc8ud1.jpeg",
            "nsfw": false,
            "spoiler": false,
            "author": "perfectgirl_1",
            "ups": 0
        },
        {
            "postLink": "https://redd.it/1g0y4j0",
            "subreddit": "sciencememes",
            "title": "a genius",
            "url": "https://i.redd.it/vti13p3611ud1.jpeg",
            "nsfw": false,
            "spoiler": false,
            "author": "perfectgirl_1",
            "ups": 16
        },
        {
            "postLink": "https://redd.it/1g0ywbj",
            "subreddit": "sciencememes",
            "title": "you dont understand the gravity of the situation",
            "url": "https://i.redd.it/1dhjkpbn81ud1.png",
            "nsfw": false,
            "spoiler": false,
            "author": "kitty_loove__",
            "ups": 100
        },
        {
            "postLink": "https://redd.it/1g1svjg",
            "subreddit": "sciencememes",
            "title": "no doubt",
            "url": "https://i.redd.it/hz7pgvi5c9ud1.jpeg",
            "nsfw": false,
            "spoiler": false,
            "author": "cleanbebe2398",
            "ups": 28
        },
        {
            "postLink": "https://redd.it/1g1hd73",
            "subreddit": "sciencememes",
            "title": "Come to think of it",
            "url": "https://i.redd.it/8cxrtgy6d6ud1.jpeg",
            "nsfw": false,
            "spoiler": false,
            "author": "zestful_aurie9342",
            "ups": 31
        },
        {
            "postLink": "https://redd.it/1g1b5hi",
            "subreddit": "sciencememes",
            "title": "Scientist by chance, not by choice. lol",
            "url": "https://i.redd.it/82v05shu05ud1.jpeg",
            "nsfw": false,
            "spoiler": false,
            "author": "Ava_Pudding_50",
            "ups": 4
        },
        {
            "postLink": "https://redd.it/1g1vxcx",
            "subreddit": "sciencememes",
            "title": "I mean, could've happened....",
            "url": "https://i.redd.it/27igupstgaud1.png",
            "nsfw": false,
            "spoiler": false,
            "author": "mommyy_livv",
            "ups": 112
        },
        {
            "postLink": "https://redd.it/1g1vcr6",
            "subreddit": "sciencememes",
            "title": "i dont know either",
            "url": "https://i.redd.it/se4d6uwq8aud1.png",
            "nsfw": false,
            "spoiler": false,
            "author": "whimsypixie_",
            "ups": 212
        },
        {
            "postLink": "https://redd.it/1g1sw7z",
            "subreddit": "sciencememes",
            "title": "Very simple",
            "url": "https://i.redd.it/ulgu44cec9ud1.png",
            "nsfw": false,
            "spoiler": false,
            "author": "AmaraLiHearts",
            "ups": 1301
        },
        {
            "postLink": "https://redd.it/1g134ma",
            "subreddit": "sciencememes",
            "title": "am wet lol",
            "url": "https://i.redd.it/gzhjgx66i2ud1.jpeg",
            "nsfw": false,
            "spoiler": false,
            "author": "steeptania8168",
            "ups": 20
        },
        {
            "postLink": "https://redd.it/1g1t9w9",
            "subreddit": "sciencememes",
            "title": "Just got some science stickers and need help understanding some",
            "url": "https://i.redd.it/o7z4vh23h9ud1.jpeg",
            "nsfw": false,
            "spoiler": false,
            "author": "Juanitajstillman",
            "ups": 0
        },
        {
            "postLink": "https://redd.it/1g0sg4f",
            "subreddit": "sciencememes",
            "title": "The teacher is wrong",
            "url": "https://i.redd.it/8ern1nohoztd1.jpeg",
            "nsfw": false,
            "spoiler": false,
            "author": "No_Tip_7615",
            "ups": 2304
        },
        {
            "postLink": "https://redd.it/1g1tkbw",
            "subreddit": "sciencememes",
            "title": "Time traveler",
            "url": "https://i.redd.it/5cdg9ippk9ud1.jpeg",
            "nsfw": false,
            "spoiler": false,
            "author": "retiredkacy8761",
            "ups": 0
        },
        {
            "postLink": "https://redd.it/1g15xgl",
            "subreddit": "sciencememes",
            "title": "this will guarantee passing the exam!",
            "url": "https://i.redd.it/97c5rhrjk3ud1.jpeg",
            "nsfw": false,
            "spoiler": false,
            "author": "Medium-Cods",
            "ups": 6
        },
        {
            "postLink": "https://redd.it/1g16mha",
            "subreddit": "sciencememes",
            "title": "We're gonna make it",
            "url": "https://i.redd.it/lkx04r9it3ud1.jpeg",
            "nsfw": false,
            "spoiler": false,
            "author": "Nicole_Honeybun_47",
            "ups": 27
        },
        {
            "postLink": "https://redd.it/1g1532a",
            "subreddit": "sciencememes",
            "title": "Real",
            "url": "https://i.redd.it/i91rlkjw83ud1.jpeg",
            "nsfw": false,
            "spoiler": false,
            "author": "GS737",
            "ups": 907
        },
        {
            "postLink": "https://redd.it/1g14vqj",
            "subreddit": "sciencememes",
            "title": "It\u2019s always algebra",
            "url": "https://i.redd.it/e4r9uyd063ud1.jpeg",
            "nsfw": false,
            "spoiler": false,
            "author": "chloemarini",
            "ups": 17
        },
        {
            "postLink": "https://redd.it/1g148eg",
            "subreddit": "sciencememes",
            "title": "that does make sense...",
            "url": "https://i.redd.it/lnx9cg1tw2ud1.png",
            "nsfw": false,
            "spoiler": false,
            "author": "adriiluuvs",
            "ups": 13
        },
        {
            "postLink": "https://redd.it/1g1cttj",
            "subreddit": "sciencememes",
            "title": "its balanced but crazy",
            "url": "https://i.redd.it/ukyx6gzyd5ud1.jpeg",
            "nsfw": false,
            "spoiler": false,
            "author": "chloemarini",
            "ups": 423
        },
        {
            "postLink": "https://redd.it/1g1si8w",
            "subreddit": "sciencememes",
            "title": "How bad can it be?",
            "url": "https://i.redd.it/4wpq7zdx79ud1.jpeg",
            "nsfw": false,
            "spoiler": false,
            "author": "yodellingleigh3033",
            "ups": 133
        },
        {
            "postLink": "https://redd.it/1g1up3p",
            "subreddit": "sciencememes",
            "title": "The surprising component.",
            "url": "https://i.redd.it/8tjh8ahmz9ud1.jpeg",
            "nsfw": false,
            "spoiler": false,
            "author": "brainysophie3579",
            "ups": 4
        },
        {
            "postLink": "https://redd.it/1g1mygw",
            "subreddit": "sciencememes",
            "title": "They did Rosalind Franklin dirty and she shouldn't be reduced to a footnote in the history of DNA research.",
            "url": "https://i.redd.it/j90x3mgdn7ud1.jpeg",
            "nsfw": false,
            "spoiler": false,
            "author": "giantlenka3686",
            "ups": 15
        },
        {
            "postLink": "https://redd.it/1g1g0bz",
            "subreddit": "sciencememes",
            "title": "Chemistry students' passwords...can't be too weak or too strong, just right",
            "url": "https://i.redd.it/bthejbgj26ud1.jpeg",
            "nsfw": false,
            "spoiler": false,
            "author": "Odd-Citron-8148",
            "ups": 3
        },
        {
            "postLink": "https://redd.it/1g1cyjv",
            "subreddit": "sciencememes",
            "title": "Found this on an old odd1sout video",
            "url": "https://i.redd.it/2gwu7x50f5ud1.png",
            "nsfw": false,
            "spoiler": false,
            "author": "ivanrj7j",
            "ups": 5
        },
        {
            "postLink": "https://redd.it/1g0zml8",
            "subreddit": "sciencememes",
            "title": "I shudder at the thought. That's like, my worst nightmare. Forgetting one.",
            "url": "https://i.redd.it/q25yeh6of1ud1.jpeg",
            "nsfw": false,
            "spoiler": false,
            "author": "BrunettieCutie",
            "ups": 57
        },
        {
            "postLink": "https://redd.it/1g18ufm",
            "subreddit": "sciencememes",
            "title": "Classical Physics: Why can't you just be predictable? Quantum Physics: Chaos intensifies",
            "url": "https://i.redd.it/dd5iu9f8h4ud1.jpeg",
            "nsfw": false,
            "spoiler": false,
            "author": "CinderellaBliss",
            "ups": 55
        },
        {
            "postLink": "https://redd.it/1g14d5w",
            "subreddit": "sciencememes",
            "title": "Living proof that sometimes, ignorance really is blissful and everlasting.",
            "url": "https://i.redd.it/cbwmbndhy2ud1.jpeg",
            "nsfw": false,
            "spoiler": false,
            "author": "KinkyAngelLover",
            "ups": 1624
        },
        {
            "postLink": "https://redd.it/1g0f3ap",
            "subreddit": "sciencememes",
            "title": "*Inhales deeply",
            "url": "https://i.redd.it/acay6fg7hwtd1.jpeg",
            "nsfw": false,
            "spoiler": false,
            "author": "Beginning-Fox-4994",
            "ups": 1131
        },
        {
            "postLink": "https://redd.it/1g0ag8l",
            "subreddit": "sciencememes",
            "title": "yuuup",
            "url": "https://i.redd.it/dfxnf78zrutd1.png",
            "nsfw": false,
            "spoiler": false,
            "author": "kitty_loove__",
            "ups": 10297
        },
        {
            "postLink": "https://redd.it/1g0x3jd",
            "subreddit": "sciencememes",
            "title": "100% accurate",
            "url": "https://i.redd.it/hvxuozyhr0ud1.jpeg",
            "nsfw": false,
            "spoiler": false,
            "author": "SukiMarquezz",
            "ups": 76
        },
        {
            "postLink": "https://redd.it/1g172zh",
            "subreddit": "sciencememes",
            "title": "Front benchers obeying like angels, while backbenchers are on another level",
            "url": "https://i.redd.it/75tcdzgvy3ud1.jpeg",
            "nsfw": false,
            "spoiler": false,
            "author": "Ok_Maintenance4530",
            "ups": 6
        },
        {
            "postLink": "https://redd.it/1g0yxmg",
            "subreddit": "sciencememes",
            "title": "You have a scientist inside the kitchen",
            "url": "https://i.redd.it/lxo3t2r091ud1.png",
            "nsfw": false,
            "spoiler": false,
            "author": "HannaRayDream",
            "ups": 374
        },
        {
            "postLink": "https://redd.it/1g1a321",
            "subreddit": "sciencememes",
            "title": "\ud83d\ude02\ud83d\ude02",
            "url": "https://i.redd.it/7m2v7tc4s4ud1.jpeg",
            "nsfw": false,
            "spoiler": false,
            "author": "Ok-Aioli7287",
            "ups": 1894
        },
        {
            "postLink": "https://redd.it/1g1ta86",
            "subreddit": "sciencememes",
            "title": "2 NA",
            "url": "https://i.redd.it/xpb8h3w7h9ud1.jpeg",
            "nsfw": false,
            "spoiler": false,
            "author": "existential_girl",
            "ups": 2
        },
        {
            "postLink": "https://redd.it/1g1v3p5",
            "subreddit": "sciencememes",
            "title": "The personification of science",
            "url": "https://i.redd.it/hhgjm7175aud1.jpeg",
            "nsfw": false,
            "spoiler": false,
            "author": "southern_darda6605",
            "ups": 9
        },
        {
            "postLink": "https://redd.it/1g1c7w0",
            "subreddit": "sciencememes",
            "title": "lol",
            "url": "https://i.redd.it/6ssztg9w85ud1.jpeg",
            "nsfw": false,
            "spoiler": false,
            "author": "Apleewhy",
            "ups": 4
        },
        {
            "postLink": "https://redd.it/1g1no98",
            "subreddit": "sciencememes",
            "title": "Kind of a bad joke but made me laugh",
            "url": "https://i.redd.it/uxqostdzt7ud1.png",
            "nsfw": false,
            "spoiler": false,
            "author": "HannaRayDream",
            "ups": 70
        },
        {
            "postLink": "https://redd.it/1g1p7xf",
            "subreddit": "sciencememes",
            "title": "great idea",
            "url": "https://i.redd.it/wpmin2gy88ud1.jpeg",
            "nsfw": false,
            "spoiler": false,
            "author": "beautygirl_7",
            "ups": 6
        },
        {
            "postLink": "https://redd.it/1g1v544",
            "subreddit": "sciencememes",
            "title": "We don't need to return to monkey, we are already maximum monkey. ",
            "url": "https://i.redd.it/tavw5uis5aud1.jpeg",
            "nsfw": false,
            "spoiler": false,
            "author": "DONGBONGER3000",
            "ups": 35
        },
        {
            "postLink": "https://redd.it/1g1v769",
            "subreddit": "sciencememes",
            "title": "It's relatable",
            "url": "https://i.redd.it/xhfj81jh6aud1.png",
            "nsfw": false,
            "spoiler": false,
            "author": "Bubbly-Artemis",
            "ups": 0
        },
        {
            "postLink": "https://redd.it/1g0wqi8",
            "subreddit": "sciencememes",
            "title": "Men are just different breed",
            "url": "https://i.redd.it/hdhfv0j5o0ud1.jpeg",
            "nsfw": false,
            "spoiler": false,
            "author": "CutieeSuki",
            "ups": 1377
        },
        {
            "postLink": "https://redd.it/1g1o1qy",
            "subreddit": "sciencememes",
            "title": "wait a moment",
            "url": "https://i.redd.it/293hki6dx7ud1.jpeg",
            "nsfw": false,
            "spoiler": false,
            "author": "aabbyray",
            "ups": 7
        },
        {
            "postLink": "https://redd.it/1g1tvej",
            "subreddit": "sciencememes",
            "title": "This is the most accurate misinformation",
            "url": "https://i.redd.it/ki51gfrio9ud1.jpeg",
            "nsfw": false,
            "spoiler": false,
            "author": "sportingeuphemia4256",
            "ups": 8
        },
        {
            "postLink": "https://redd.it/1g1qqit",
            "subreddit": "sciencememes",
            "title": "one of the most dangerous things",
            "url": "https://i.redd.it/7i080gbgo8ud1.jpeg",
            "nsfw": false,
            "spoiler": false,
            "author": "Kelly_XDream",
            "ups": 1
        },
        {
            "postLink": "https://redd.it/1g1fap6",
            "subreddit": "sciencememes",
            "title": "Who needs good grades when you've got chemistry memes on your side? ",
            "url": "https://i.redd.it/ismfisxww5ud1.jpeg",
            "nsfw": false,
            "spoiler": false,
            "author": "Tight-Highway4231",
            "ups": 26
        },
        {
            "postLink": "https://redd.it/1g1l5vn",
            "subreddit": "sciencememes",
            "title": "If you know, you know",
            "url": "https://i.redd.it/6syip3d187ud1.jpeg",
            "nsfw": false,
            "spoiler": false,
            "author": "CutieeSuki",
            "ups": 158
        },
        {
            "postLink": "https://redd.it/1g0swv6",
            "subreddit": "sciencememes",
            "title": "These questions are above my paygrade.",
            "url": "https://i.redd.it/ki3nql72sztd1.png",
            "nsfw": false,
            "spoiler": false,
            "author": "Individual-Tear7186",
            "ups": 4102
        },
        {
            "postLink": "https://redd.it/1g141ra",
            "subreddit": "sciencememes",
            "title": "The surprising component.",
            "url": "https://i.redd.it/z32jhis8u2ud1.jpeg",
            "nsfw": false,
            "spoiler": false,
            "author": "naked_kathi7994",
            "ups": 12
        },
        {
            "postLink": "https://redd.it/1g0kl0v",
            "subreddit": "sciencememes",
            "title": "Listen to a person of science!",
            "url": "https://i.redd.it/21l1jyfgzxtd1.jpeg",
            "nsfw": false,
            "spoiler": false,
            "author": "Ava_Pudding_50",
            "ups": 209
        },
        {
            "postLink": "https://redd.it/1g1rj5u",
            "subreddit": "sciencememes",
            "title": "and thats the start of the argument",
            "url": "https://i.redd.it/uhk24oezw8ud1.png",
            "nsfw": false,
            "spoiler": false,
            "author": "Whole_Spare4642",
            "ups": 8559
        },
        {
            "postLink": "https://redd.it/1g1h400",
            "subreddit": "sciencememes",
            "title": "It's NORMAL",
            "url": "https://i.redd.it/ffn0ud4ab6ud1.jpeg",
            "nsfw": false,
            "spoiler": false,
            "author": "Katherinehsaville",
            "ups": 100
        },
        {
            "postLink": "https://redd.it/1g12w63",
            "subreddit": "sciencememes",
            "title": "Marx just wants to sell more clocks",
            "url": "https://i.redd.it/inwnobb4f2ud1.jpeg",
            "nsfw": false,
            "spoiler": false,
            "author": "TeasingBabex",
            "ups": 521
        },
        {
            "postLink": "https://redd.it/1g13z1p",
            "subreddit": "sciencememes",
            "title": "Retail Karens are the worst",
            "url": "https://i.redd.it/u5un6au9t2ud1.png",
            "nsfw": false,
            "spoiler": false,
            "author": "whimsypixie_",
            "ups": 70
        },
        {
            "postLink": "https://redd.it/1g1se8p",
            "subreddit": "sciencememes",
            "title": "Isn't easy to get!",
            "url": "https://i.redd.it/ezrg7e6ee6ud1.png",
            "nsfw": false,
            "spoiler": false,
            "author": "Numerous_Ad_2570",
            "ups": 653
        },
        {
            "postLink": "https://redd.it/1g0g1fq",
            "subreddit": "sciencememes",
            "title": "Mathematics bothers Thanos.",
            "url": "https://i.redd.it/633ygte6twtd1.jpeg",
            "nsfw": false,
            "spoiler": false,
            "author": "Sufficient-Fig-3364",
            "ups": 255
        },
        {
            "postLink": "https://redd.it/1g169ae",
            "subreddit": "sciencememes",
            "title": "Sorry kiddo, science is cruel",
            "url": "https://i.redd.it/uqsdqt70p3ud1.png",
            "nsfw": false,
            "spoiler": false,
            "author": "Difficult_Eagle_1307",
            "ups": 1806
        },
        {
            "postLink": "https://redd.it/1g13uqg",
            "subreddit": "sciencememes",
            "title": "genius",
            "url": "https://i.redd.it/vsdbo98nr2ud1.png",
            "nsfw": false,
            "spoiler": false,
            "author": "sassydollyyy",
            "ups": 85
        },
        {
            "postLink": "https://redd.it/1g0xnv1",
            "subreddit": "sciencememes",
            "title": "very creative",
            "url": "https://i.redd.it/um0555lvw0ud1.jpeg",
            "nsfw": false,
            "spoiler": false,
            "author": "Kelly_XDream",
            "ups": 19
        },
        {
            "postLink": "https://redd.it/1g11lw1",
            "subreddit": "sciencememes",
            "title": "completely",
            "url": "https://i.redd.it/810aj92202ud1.jpeg",
            "nsfw": false,
            "spoiler": false,
            "author": "aabbyray",
            "ups": 105
        },
        {
            "postLink": "https://redd.it/1g1w24g",
            "subreddit": "sciencememes",
            "title": "*Florida",
            "url": "https://i.redd.it/l08285epiaud1.png",
            "nsfw": false,
            "spoiler": false,
            "author": "adriiluuvs",
            "ups": 17
        },
        {
            "postLink": "https://redd.it/1g19m88",
            "subreddit": "sciencememes",
            "title": "POV when you are the MVP of the meltdown squad",
            "url": "https://i.redd.it/n3efc0g7o4ud1.jpeg",
            "nsfw": false,
            "spoiler": false,
            "author": "Wise_Iron141",
            "ups": 54
        },
        {
            "postLink": "https://redd.it/1g1641l",
            "subreddit": "sciencememes",
            "title": "Leveling up from Sugar Daddy to full scientific deity.",
            "url": "https://i.redd.it/vdfq8fanm3ud1.jpeg",
            "nsfw": false,
            "spoiler": false,
            "author": "whoopsy_girlfriennd",
            "ups": 287
        },
        {
            "postLink": "https://redd.it/1g15vc4",
            "subreddit": "sciencememes",
            "title": "yeah.....",
            "url": "https://i.redd.it/vcd3wemsj3ud1.jpeg",
            "nsfw": false,
            "spoiler": false,
            "author": "CornerFamiliars",
            "ups": 1490
        },
        {
            "postLink": "https://redd.it/1g13mjn",
            "subreddit": "sciencememes",
            "title": "Now you get it",
            "url": "https://i.redd.it/kzrgjp8lo2ud1.jpeg",
            "nsfw": false,
            "spoiler": false,
            "author": "existential_girl",
            "ups": 29
        },
        {
            "postLink": "https://redd.it/1g0eme2",
            "subreddit": "sciencememes",
            "title": "Safety and Science",
            "url": "https://i.redd.it/lbfwtiznawtd1.jpeg",
            "nsfw": false,
            "spoiler": false,
            "author": "Imaginary-Sky-1295",
            "ups": 4085
        },
        {
            "postLink": "https://redd.it/1g13fae",
            "subreddit": "sciencememes",
            "title": "Natural numbers",
            "url": "https://i.redd.it/u5gqc54yl2ud1.jpeg",
            "nsfw": false,
            "spoiler": false,
            "author": "brainysophie3579",
            "ups": 43
        },
        {
            "postLink": "https://redd.it/1g18sr1",
            "subreddit": "sciencememes",
            "title": "I can't believe what I'm hearing",
            "url": "https://i.redd.it/95uh9eqwg4ud1.jpeg",
            "nsfw": false,
            "spoiler": false,
            "author": "Esme_MoonPie_75",
            "ups": 169
        },
        {
            "postLink": "https://redd.it/1g129hg",
            "subreddit": "sciencememes",
            "title": "I don\u2019t know this science stuff",
            "url": "https://i.imgur.com/yfevfPj.jpeg",
            "nsfw": false,
            "spoiler": false,
            "author": "Consistent-Buy5688",
            "ups": 1032
        },
        {
            "postLink": "https://redd.it/1g1jbtg",
            "subreddit": "sciencememes",
            "title": "ready for sashimi",
            "url": "https://i.redd.it/5htbkxrzs6ud1.png",
            "nsfw": false,
            "spoiler": false,
            "author": "Coco_Sugar54",
            "ups": 13
        },
        {
            "postLink": "https://redd.it/1g15poo",
            "subreddit": "sciencememes",
            "title": "That escalated quickly",
            "url": "https://i.redd.it/vq9l5yeih3ud1.png",
            "nsfw": false,
            "spoiler": false,
            "author": "No-Contest9713",
            "ups": 2722
        },
        {
            "postLink": "https://redd.it/1g1ibf1",
            "subreddit": "sciencememes",
            "title": "Me when someone stole my cookie jar",
            "url": "https://i.redd.it/m3m7f3lmk6ud1.png",
            "nsfw": false,
            "spoiler": false,
            "author": "Spice_Maya88",
            "ups": 0
        },
        {
            "postLink": "https://redd.it/1g1aai2",
            "subreddit": "sciencememes",
            "title": "Isn't it odd?",
            "url": "https://i.redd.it/bv1kpxiht4ud1.png",
            "nsfw": false,
            "spoiler": false,
            "author": "Numerous_Ad_2570",
            "ups": 46
        },
        {
            "postLink": "https://redd.it/1g0e231",
            "subreddit": "sciencememes",
            "title": "lol",
            "url": "https://i.redd.it/xnncrojg2wtd1.jpeg",
            "nsfw": false,
            "spoiler": false,
            "author": "lushi11",
            "ups": 619
        }
    ]
}